mmk_ai/__init__.py
mmk_ai/auto_train.py
mmk_ai/data_preprocessing.py
mmk_ai/easy_train.py
mmk_ai/evaluation.py
mmk_ai/model_training.py
mmk_ai/scoring.py
mmk_ai/visualization.py
mmk_ai-0.7.2.dist-info/LICENSE
mmk_ai-0.7.2.dist-info/METADATA
mmk_ai-0.7.2.dist-info/WHEEL
mmk_ai-0.7.2.dist-info/top_level.txt
mmk_ai-0.7.2.dist-info/RECORD
